{"id": 239, "uuid": "15c172aa-8b18-4de0-929a-f896cce3a0ff", "name": "oadr3", "version": null, "status": "active", "desc": "OpenADR 3.1 VEN Plugin for IoX", "docs": "docs", "url": null, "branch": null, "language": "python3", "executable": "oadr3.py", "install": "install.sh", "developer": "tech@universal-devices.com", "nsdata": null, "oauth": null, "purchaseOptions": "[]", "author": "UD", "devMode": 1, "devPath": "/home/admin/workspace/plugin-dev/oadr3", "devUser": "admin", "shortPoll": 60, "longPoll": 600, "nsInfoPoll": 60, "logLevel": "DEBUG", "logLevelList": null, "customParams": null, "persist_folder": null, "profile_version": "3.0.0", "readme": null, "changelog": null, "store": "Local", "devd": null, "discover": 0, "authorize": 0, "polisy": 1, "eisy": 1, "isyAccess": 1, "fileUpload": 0, "packageList": null, "license": "lic", "ip_added": "localhost", "ts_added": 1762825315, "ts_updated": 1762825315, "slot": 3}