<editors><editor id="on_off">
<range uom="25" min="0" max="1" nls="NLSIX_on_off"/>
</editor>
<editor id="ready">
<range uom="25" min="0" max="1" nls="NLSIX_ready"/>
</editor>
<editor id="yes_no">
<range uom="25" min="0" max="1" nls="NLSIX_yes_no"/>
</editor>
<editor id="frequency">
<range uom="90" min="0" max="100000" prec="2" step="1"/>
</editor>
<editor id="current">
<range uom="1" min="0" max="1000" prec="2" step="1"/>
</editor>
<editor id="pressure">
<range uom="138" min="0" max="1000" step="0"/>
</editor>
<editor id="voltage">
<range uom="72" min="-500" max="500" prec="2" step="1"/>
</editor>
<editor id="CTL_BOOL">
<range uom="2" min="0" max="1"/>
</editor>
</editors>